src/__init__.py
src/functional.py
src/rec_metrics.py
recmetrics_sweep-0.0.0.dist-info/LICENSE
recmetrics_sweep-0.0.0.dist-info/METADATA
recmetrics_sweep-0.0.0.dist-info/WHEEL
recmetrics_sweep-0.0.0.dist-info/top_level.txt
recmetrics_sweep-0.0.0.dist-info/RECORD
