Metadata-Version: 2.1
Name: recmetrics-sweep
Version: 0.0.0
Summary: Execute all desired rec metrics at once, quickly, including with different values of k.
Home-page: https://github.com/JoshuaMathias/recmetrics_sweep
Author: Joshua Mathias
Author-email: joshuaamathias@gmail.com
License: UNKNOWN
Keywords: recommendation,recommender systems,evaluation,metrics
Platform: UNKNOWN
Classifier: Programming Language :: Python :: 3
Classifier: License :: OSI Approved :: MIT License
Classifier: Operating System :: OS Independent
